{
    "recipes": 
    [
        {
            "name": "Pelmeni",
            "origin": "Eastern European",
            "time-to-cook": 15,
            "image-source": "prosto-eats/images/pelmeni-cover.jpg"
        },

        {
            "name": "Burger & Fries",
            "origin": "United States",
            "time-to-cook": 20,
            "image-source": "prosto-eats/images/burger-cover.jpg"
        },
        
        {
            "name": "Garlic Pasta & Cooked Chicken",
            "origin": "Southern Europe",
            "time-to-cook": 25,
            "image-source": "prosto-eats/images/pelmeni-cover.jpg"

        }
    ]

}